openmemobird/__init__.py
openmemobird/memobird.py
openmemobird-1.0.0a3.dist-info/LICENSE
openmemobird-1.0.0a3.dist-info/METADATA
openmemobird-1.0.0a3.dist-info/WHEEL
openmemobird-1.0.0a3.dist-info/top_level.txt
openmemobird-1.0.0a3.dist-info/RECORD
