Metadata-Version: 2.1
Name: openmemobird
Version: 1.0.0a3
Summary: Package to send data and documents to Memobird printers.
Home-page: https://github.com/leminaw/openmemobird
Author: LeMinaw
Author-email: le@minaw.net
License: UNKNOWN
Platform: UNKNOWN
Classifier: Programming Language :: Python :: 3
Classifier: Development Status :: 3 - Alpha
Classifier: License :: OSI Approved :: MIT License
Classifier: Operating System :: OS Independent
Requires-Dist: requests (>=2.0.0)
Requires-Dist: Pillow (>=5.0.0)
